htt/__init__.py
htt/application.py
htt/exceptions.py
htt/grpc.py
htt/logging.py
htt/path.py
htt/protobuf/__init__.py
htt/protobuf/dict.py
htt/protobuf/environ.py
htt/protobuf/json.py
htt/protobuf/yaml.py
htt/py.typed
htt/pytest_skip_dev.py
htt/timer.py
htt-0.35.dist-info/LICENSE
htt-0.35.dist-info/METADATA
htt-0.35.dist-info/WHEEL
htt-0.35.dist-info/RECORD
